infobvc/__init__.py
infobvc/core.py
infobvc-0.0.4.dist-info/LICENSE
infobvc-0.0.4.dist-info/METADATA
infobvc-0.0.4.dist-info/WHEEL
infobvc-0.0.4.dist-info/top_level.txt
infobvc-0.0.4.dist-info/RECORD
